README.md
setup.cfg
setup.py
hsw2v.egg-info/PKG-INFO
hsw2v.egg-info/SOURCES.txt
hsw2v.egg-info/dependency_links.txt
hsw2v.egg-info/requires.txt
hsw2v.egg-info/top_level.txt
w2v/__init__.py
w2v/collation.py
w2v/datasets.py
w2v/frequencies.py
w2v/inputs.py
w2v/neg_sampling.py
w2v/preprocessing.py
w2v/readers.py
w2v/subsampling.py
w2v/tokenization.py
w2v/vocabulary.py