Metadata-Version: 1.1
Name: hsw2v
Version: 1.0a1
Summary: Word2vec utility classes.
Home-page: https://github.com/timniven/w2v
Author: Tim Niven
Author-email: tim.niven.public@gmail.com
License: MIT
Download-URL: https://github.com/timniven/w2v/archive/1.0a1.tar.gz
Keywords: wor2vec nlp
Platform: UNKNOWN
Classifier: Development Status :: 3 - Alpha
Classifier: Intended Audience :: Developers
Classifier: Topic :: Software Development :: Libraries :: Python Modules
Classifier: Programming Language :: Python :: 3
Classifier: License :: OSI Approved :: MIT License
